mpljourney/__init__.py
mpljourney/main.py
mpljourney-0.1.0.dist-info/licenses/LICENSE
mpljourney-0.1.0.dist-info/METADATA
mpljourney-0.1.0.dist-info/WHEEL
mpljourney-0.1.0.dist-info/top_level.txt
mpljourney-0.1.0.dist-info/RECORD
