Metadata-Version: 2.4
Name: mpljourney
Version: 0.1.0
Summary: A collection of cool datasets for Python.
Author-email: Joseph Barbier <joseph.barbierdarnal@mail.com>
License-Expression: MIT
Project-URL: Homepage, https://github.com/JosephBARBIERDARNAL/mpljourney
Project-URL: Issues, https://github.com/JosephBARBIERDARNAL/mpljourney/issues
Project-URL: Documentation, https://github.com/JosephBARBIERDARNAL/mpljourney
Project-URL: Repository, https://github.com/JosephBARBIERDARNAL/mpljourney
Keywords: datasets,data,exploration,matplotlib,journey,visualization,analysis
Classifier: Programming Language :: Python :: 3
Classifier: Operating System :: OS Independent
Classifier: Development Status :: 3 - Alpha
Requires-Python: >=3.9
License-File: LICENSE
Requires-Dist: narwhals>=1.0.0
Provides-Extra: geo
Requires-Dist: geopandas>=1.0.1; extra == "geo"
Dynamic: license-file
